verilog/02_full_adder/test.sv
/*

cin a b  s cout p g
0 0 0 - 0 0 0 0
0 0 1 - 1 0 1 0
0 1 0 - 1 0 1 0
0 1 1 - 0 1 1 1
1 0 0 - 1 0 0 0
1 0 1 - 0 1 1 0
1 1 0 - 0 1 1 0
1 1 1 - 1 1 1 1


*/

module test(
	input logic cin, a, b,
	output logic s, cout, p, g);
	
	assign p = a | b;
	assign g = a & b;

	assign s = a ^ b ^ cin;
	assign cout = (a & b) | (a & cin) | (b & cin);
endmodule

verilog/02_full_adder/test_tb.sv
`timescale 1ns / 1ps

module testbench();
	
	// bookkeeping
	logic [31:0] i, errs;
	logic [6:0] inputs[0:7];

	// signals
	logic cin, a, b, s, cout, p, g, exp_s, exp_cout, exp_p, exp_g;

	// instantiate UUT
	test uut(cin, a, b, s, cout, p, g);

	// initialize input and output files
	initial begin 
		// load test inputs file
		$readmemb("vectors.txt", inputs);
		i = 0; errs = 0;

		// wave file
		$dumpfile("wave.vcd");
		$dumpvars(0, uut);
	end

	// apply test vectors on rising edge of clk
	always begin 
		{cin, a, b, exp_s, exp_cout, exp_p, exp_g} = inputs[i];
		#1;
		if (s != exp_s || p != exp_p || g != exp_g || cout != exp_cout) begin // check result
			$display("Error: inputs = %b outputs = %b (%b expected)", {cin, a, b}, {s, cout, p, g}, {exp_s, exp_cout, exp_p, exp_g});
			errs = errs + 1;
		end
		i = i + 1;
		if (inputs[i] === 7'bx) begin 
			$display("%d tests completed with %d errors", i, errs);
			$finish;
		end
	end

endmodule

verilog/02_full_adder/wave.vcd
$date
	Thu Sep  8 03:26:35 2022
$end
$version
	Icarus Verilog
$end
$timescale
	1ps
$end
$scope module testbench $end
$scope module uut $end
$var wire 1 ! a $end
$var wire 1 " b $end
$var wire 1 # cin $end
$var wire 1 $ cout $end
$var wire 1 % g $end
$var wire 1 & p $end
$var wire 1 ' s $end
$upscope $end
$upscope $end
$enddefinitions $end
#0
$dumpvars
0'
0&
0%
0$
0#
0"
0!
$end
#1000
1'
1&
1"
#2000
1!
0"
#3000
1$
0'
1%
1"
#4000
0$
1'
0&
0%
1#
0!
0"
#5000
0'
1$
1&
1"
#6000
1$
1!
0"
#7000
1'
1%
1"
